Gh0stSimpleDiagramTool/__init__.py
Gh0stSimpleDiagramTool/simple_diagram_tool.py
Gh0stSimpleDiagramTool-0.0.4.dist-info/LICENSE
Gh0stSimpleDiagramTool-0.0.4.dist-info/METADATA
Gh0stSimpleDiagramTool-0.0.4.dist-info/WHEEL
Gh0stSimpleDiagramTool-0.0.4.dist-info/top_level.txt
Gh0stSimpleDiagramTool-0.0.4.dist-info/RECORD
