Metadata-Version: 2.1
Name: Gh0stSimpleDiagramTool
Version: 0.0.4
Summary: A simple diagram drawing tool
Home-page: https://github.com/gh0stintheshe11/gh0st-SImpleDiagramTool
Author: gh0stintheshe11
Author-email: gh0stintheshe11@gmail.com
License: MIT
Keywords: diagram flowchart matplotlib
License-File: LICENSE
Requires-Dist: matplotlib
